webob_view
