Metadata-Version: 1.0
Name: webob_view
Version: 0.6
Summary: paste template for a view using webob
Home-page: http://k0s.org
Author: Jeff Hammel
Author-email: jhammel@openplans.org
License: GPL
Platform: UNKNOWN
